pronouns_test_data/__init__.py
pronouns_test_data/data/0.1.0.csv
pronouns_test_data/data/0.1.0.json
pronouns_test_data/data/1.0.0.csv
pronouns_test_data/data/1.0.0.json
pronouns_test_data/data/latest.csv
pronouns_test_data/data/latest.json
pronouns_test_data/generate.py
pronouns_test_data/models.py
pronouns_test_data/publish.py
pronouns_test_data-1.0.0.dist-info/LICENSE
pronouns_test_data-1.0.0.dist-info/WHEEL
pronouns_test_data-1.0.0.dist-info/METADATA
pronouns_test_data-1.0.0.dist-info/RECORD
